malcolm3utils/__init__.py
malcolm3utils/py.typed
malcolm3utils/scripts/getcol.py
malcolm3utils/scripts/merge.py
malcolm3utils/scripts/touch_latest.py
malcolm3utils-0.5.7.dist-info/LICENCE
malcolm3utils-0.5.7.dist-info/METADATA
malcolm3utils-0.5.7.dist-info/WHEEL
malcolm3utils-0.5.7.dist-info/entry_points.txt
malcolm3utils-0.5.7.dist-info/RECORD
