Metadata-Version: 2.3
Name: malcolm3utils
Version: 0.5.7
Summary: Collection of Utility Scripts and Packages
License: BSD-3-Clause
Author: Malcolm E. Davis
Author-email: mnjjunk@comcast.net
Requires-Python: >=3.9,<4.0
Classifier: Development Status :: 4 - Beta
Classifier: Intended Audience :: Developers
Classifier: License :: OSI Approved :: BSD License
Classifier: Operating System :: OS Independent
Classifier: Programming Language :: Python
Classifier: Programming Language :: Python :: 3
Classifier: Programming Language :: Python :: 3.9
Classifier: Programming Language :: Python :: 3.10
Classifier: Programming Language :: Python :: 3.11
Classifier: Programming Language :: Python :: 3.12
Classifier: Programming Language :: Python :: 3.13
Classifier: Topic :: Desktop Environment
Classifier: Typing :: Typed
Requires-Dist: click-logging (>=1.0.1,<2.0.0)
Requires-Dist: requests (>=2.32.4)
Requires-Dist: urllib3 (>=2.5.0)
Project-URL: Documentation, https://malcolm-3.github.io/malcolm3utils
Project-URL: Homepage, https://malcolm-3.github.io/malcolm3utils
Project-URL: Repository, https://github.com/malcolm-3/malcolm3utils
